scrapy_redis/__init__.py
scrapy_redis/connection.py
scrapy_redis/defaults.py
scrapy_redis/dupefilter.py
scrapy_redis/picklecompat.py
scrapy_redis/pipelines.py
scrapy_redis/queue.py
scrapy_redis/scheduler.py
scrapy_redis/spiders.py
scrapy_redis/stats.py
scrapy_redis/utils.py
latest_scrapy_redis-0.7.3.dist-info/AUTHORS.rst
latest_scrapy_redis-0.7.3.dist-info/LICENSE
latest_scrapy_redis-0.7.3.dist-info/METADATA
latest_scrapy_redis-0.7.3.dist-info/WHEEL
latest_scrapy_redis-0.7.3.dist-info/top_level.txt
latest_scrapy_redis-0.7.3.dist-info/RECORD
