Metadata-Version: 2.1
Name: latest-scrapy-redis
Version: 0.7.3
Summary: Redis-based components for Scrapy.
Home-page: https://github.com/Ehsan-U/scrapy-redis
Author: Ehsan U.
Author-email: au85265@gmail.com
License: MIT
Keywords: scrapy-redis
Classifier: Development Status :: 4 - Beta
Classifier: Intended Audience :: Developers
Classifier: License :: OSI Approved :: MIT License
Classifier: Natural Language :: English
Classifier: Programming Language :: Python :: 3
Classifier: Programming Language :: Python :: 3.7
Classifier: Programming Language :: Python :: 3.8
Classifier: Programming Language :: Python :: 3.9
Classifier: Programming Language :: Python :: 3.10
License-File: LICENSE
License-File: AUTHORS.rst
Requires-Dist: scrapy >=2.6.0
Requires-Dist: redis >=4.2
Requires-Dist: six >=1.15
